Metadata-Version: 1.0
Name: dist-gaussian-binomial
Version: 1.1
Summary: Probability Distributions - Gaussian and Binomial
Home-page: UNKNOWN
Author: Manish Agrawal
Author-email: UNKNOWN
License: UNKNOWN
Platform: UNKNOWN
